pylayerize/__init__.py
pylayerize/__main__.py
pylayerize/Dockerfiles/git_private_package.Dockerfile
pylayerize/Dockerfiles/local_install.Dockerfile
pylayerize/Dockerfiles/single_pypi_package.Dockerfile
pylayerize/core/__init__.py
pylayerize/core/docker/__init__.py
pylayerize/core/docker/docker.py
pylayerize/util/__init__.py
pylayerize/util/args_util.py
pylayerize/util/logging_util.py
pylayerize-1.0.1.dist-info/METADATA
pylayerize-1.0.1.dist-info/WHEEL
pylayerize-1.0.1.dist-info/entry_points.txt
pylayerize-1.0.1.dist-info/top_level.txt
pylayerize-1.0.1.dist-info/RECORD
