Metadata-Version: 2.1
Name: pylayerize
Version: 1.0.1
Summary: pylayerize simplifies the process of creating AWS Lambda Layers by leveraging Docker to compile and package Python dependencies for any targeted runtime. With support for custom packages and private GitHub repos, pylayerize optimizes the creation and deployment of Lambda Layers for improved development efficiency.
Home-page: https://github.com/JamMassey/lambda-layer-builder
Author: James Massey
Author-email: jammassey@hotmail.com
Keywords: aws lambda layer pylayerize pylayerizer pylayerize
Classifier: Development Status :: 5 - Production/Stable
Classifier: Intended Audience :: Developers
Classifier: Topic :: Software Development :: Build Tools
Classifier: Programming Language :: Python :: 3
Classifier: Programming Language :: Python :: 3.7
Classifier: Programming Language :: Python :: 3.8
Classifier: Programming Language :: Python :: 3.9
Classifier: Programming Language :: Python :: 3 :: Only
Classifier: License :: OSI Approved :: MIT License
Classifier: Operating System :: OS Independent
Requires-Python: >=3.7
Provides-Extra: dev
Requires-Dist: check-manifest ; extra == 'dev'
